[{"dt":"2024-11-24 00:31:21","id":68225,"name":"3213张","age":"萌","sex":"女"},{"dt":"2024-11-24 00:31:22","id":35673,"name":"张萌2","age":"2213","sex":"男"},{"dt":"2024-11-24 00:31:49","id":82941,"name":"312312","age":"312","sex":"男"},{"dt":"2024-11-24 14:38:02","id":45175,"name":"张萌","age":"88","sex":"女"},{"dt":"2024-11-24 14:38:26","id":97250,"name":"萌","age":"88","sex":"男"},{"dt":"2024-11-24 14:38:42","id":15365,"name":"31233123213","age":"312312","sex":"女"},{"dt":"2024-11-24 14:43:14","id":64100,"name":"3123312312","age":"123123123","sex":"女"},{"dt":"2024-11-24 14:43:26","id":31274,"name":"321321","age":"3213","sex":"男"},{"dt":"2024-11-24 14:43:42","id":78606,"name":"呃3213","age":"1231","sex":"男"}]